ldc_xac/__init__.py
ldc_xac/api_caller.py
ldc_xac/config.py
ldc_xac/constants.py
ldc_xac-1.0.5.dist-info/licenses/LICENSE
ldc_xac-1.0.5.dist-info/METADATA
ldc_xac-1.0.5.dist-info/WHEEL
ldc_xac-1.0.5.dist-info/top_level.txt
ldc_xac-1.0.5.dist-info/RECORD
