Metadata-Version: 2.4
Name: ldc-xac
Version: 1.0.5
Summary: External API Caller with comprehensive logging
Home-page: https://github.com/ayushsonar-lendenclub/ldc-xac
Author: Ayush Sonar
Author-email: Ayush Sonar <ayush.sonar@lendenclub.com>
License: MIT
Project-URL: Homepage, https://github.com/ayushsonar-lendenclub/ldc-xac
Project-URL: Repository, https://github.com/ayushsonar-lendenclub/ldc-xac
Project-URL: Issues, https://github.com/ayushsonar-lendenclub/ldc-xac
Keywords: api,http,requests,logging,external-api
Classifier: Development Status :: 4 - Beta
Classifier: Intended Audience :: Developers
Classifier: License :: OSI Approved :: MIT License
Classifier: Operating System :: OS Independent
Classifier: Programming Language :: Python :: 3
Classifier: Programming Language :: Python :: 3.7
Classifier: Programming Language :: Python :: 3.8
Classifier: Programming Language :: Python :: 3.9
Classifier: Programming Language :: Python :: 3.10
Classifier: Programming Language :: Python :: 3.11
Classifier: Programming Language :: Python :: 3.12
Requires-Python: >=3.7
License-File: LICENSE
Requires-Dist: requests>=2.25.0
Provides-Extra: dev
Requires-Dist: pytest>=6.0; extra == "dev"
Requires-Dist: pytest-cov>=2.0; extra == "dev"
Requires-Dist: black>=21.0; extra == "dev"
Requires-Dist: flake8>=3.8; extra == "dev"
Requires-Dist: mypy>=0.800; extra == "dev"
Dynamic: author
Dynamic: home-page
Dynamic: license-file
Dynamic: requires-python
